hermes_odin_nodes/__init__.py
hermes_odin_nodes/odin_stream_node.py
hermes_odin_nodes-1.0.0.dist-info/METADATA
hermes_odin_nodes-1.0.0.dist-info/WHEEL
hermes_odin_nodes-1.0.0.dist-info/RECORD
