Metadata-Version: 2.4
Name: hermes-odin-nodes
Version: 1.0.0
Summary: nodes for interacting with ODIN
Author-email: floris vernieuwe <floris@vernieuwe.eu>
Requires-Python: >=3.10
Requires-Dist: burst-link-protocol>=1.1.4
Requires-Dist: hermes-framing-nodes>=1.0.1
Requires-Dist: hermes-stream-nodes>=1.0.1
Requires-Dist: node-hermes-core>=1.2.0
Requires-Dist: odin-stream>=0.1.4
Requires-Dist: polars>=1.30.0
